clapper/__init__.py
clapper/click.py
clapper/config.py
clapper/logging.py
clapper/rc.py
clapper-1.3.2.dist-info/METADATA
clapper-1.3.2.dist-info/WHEEL
clapper-1.3.2.dist-info/entry_points.txt
clapper-1.3.2.dist-info/RECORD
